qiskit_ionq/__init__.py
qiskit_ionq/constants.py
qiskit_ionq/exceptions.py
qiskit_ionq/helpers.py
qiskit_ionq/ionq_backend.py
qiskit_ionq/ionq_client.py
qiskit_ionq/ionq_equivalence_library.py
qiskit_ionq/ionq_gates.py
qiskit_ionq/ionq_job.py
qiskit_ionq/ionq_optimizer_plugin.py
qiskit_ionq/ionq_provider.py
qiskit_ionq/ionq_result.py
qiskit_ionq/ionq_session.py
qiskit_ionq/py.typed
qiskit_ionq/rewrite_rules.py
qiskit_ionq/version.py
qiskit_ionq-1.0.2.dist-info/licenses/LICENSE.txt
qiskit_ionq-1.0.2.dist-info/METADATA
qiskit_ionq-1.0.2.dist-info/WHEEL
qiskit_ionq-1.0.2.dist-info/top_level.txt
qiskit_ionq-1.0.2.dist-info/RECORD
