Metadata-Version: 2.4
Name: qiskit-ionq
Version: 1.0.2
Summary: Qiskit provider for IonQ backends
Home-page: https://github.com/qiskit-community/qiskit-ionq
Author: IonQ
Author-email: info@ionq.com
License: Apache 2.0
Project-URL: Bug Tracker, https://github.com/qiskit-community/qiskit-ionq/issues
Project-URL: Source Code, https://github.com/qiskit-community/qiskit-ionq
Keywords: qiskit sdk quantum
Classifier: Environment :: Console
Classifier: License :: OSI Approved :: Apache Software License
Classifier: Intended Audience :: Developers
Classifier: Intended Audience :: Science/Research
Classifier: Operating System :: Microsoft :: Windows
Classifier: Operating System :: MacOS
Classifier: Operating System :: POSIX :: Linux
Classifier: Programming Language :: Python :: 3 :: Only
Classifier: Programming Language :: Python :: 3.10
Classifier: Programming Language :: Python :: 3.11
Classifier: Programming Language :: Python :: 3.12
Classifier: Programming Language :: Python :: 3.13
Classifier: Topic :: Scientific/Engineering
Requires-Python: >=3.10
License-File: LICENSE.txt
Requires-Dist: qiskit>=2.0.0
Requires-Dist: decorator>=5.1.0
Requires-Dist: requests>=2.24.0
Requires-Dist: importlib-metadata>=4.11.4
Requires-Dist: python-dotenv>=1.0.1
Provides-Extra: test
Requires-Dist: qiskit>=2.0.0; extra == "test"
Requires-Dist: pytest; extra == "test"
Requires-Dist: requests-mock>=1.8.0; extra == "test"
Requires-Dist: pytest-cov>=2.10.1; extra == "test"
Dynamic: author
Dynamic: author-email
Dynamic: classifier
Dynamic: description
Dynamic: description-content-type
Dynamic: home-page
Dynamic: keywords
Dynamic: license
Dynamic: license-file
Dynamic: project-url
Dynamic: provides-extra
Dynamic: requires-dist
Dynamic: requires-python
Dynamic: summary
